prlsp_dnsbl/__init__.py
prlsp_dnsbl/domains/all_dnsbl_domains.json
prlsp_dnsbl/domains/base_dnsbl_domains.json
prlsp_dnsbl-0.0.1a0.dist-info/LICENSE.txt
prlsp_dnsbl-0.0.1a0.dist-info/METADATA
prlsp_dnsbl-0.0.1a0.dist-info/WHEEL
prlsp_dnsbl-0.0.1a0.dist-info/top_level.txt
prlsp_dnsbl-0.0.1a0.dist-info/RECORD
