Metadata-Version: 2.1
Name: prlsp_dnsbl
Version: 0.0.1a0
Summary: проверка ip по базам dns-based blacklist
Home-page: https://github.com/prolapser/prlsp_dnsbl
Author: prolapser
License: LICENSE.txt
Classifier: Development Status :: 4 - Beta
Classifier: Intended Audience :: Developers
Classifier: License :: OSI Approved :: MIT License
Classifier: Operating System :: OS Independent
Requires-Python: >=3.10
License-File: LICENSE.txt
Requires-Dist: aiodns
Requires-Dist: pycares
